{"name":"searchBySingleKeyword","id":"starter.wikipedia.WhenSearchingForTerms:searchBySingleKeyword","testCaseName":"starter.wikipedia.WhenSearchingForTerms","testSteps":[{"number":1,"description":"Navigate to the home page","duration":8545,"startTime":"2023-01-22T16:13:27.960964566Z[Etc/UTC]","screenshots":[{"screenshot":"5dcf0cfd474cdd28cb8e821fce0fbd5f97446743aa752c2db505a3c6dfd3b543.png","timeStamp":1674404016506,"screenshotName":"5dcf0cfd474cdd28cb8e821fce0fbd5f97446743aa752c2db505a3c6dfd3b543.png"}],"result":"SUCCESS","precondition":false,"level":0},{"number":2,"description":"Search by keyword \u0027Everest\u0027","duration":1539,"startTime":"2023-01-22T16:13:36.509352822Z[Etc/UTC]","screenshots":[{"screenshot":"b9cf047bbb123c27c2b654e585627d8511a44eccdd9143388660055dc83782bb.png","timeStamp":1674404018048,"screenshotName":"b9cf047bbb123c27c2b654e585627d8511a44eccdd9143388660055dc83782bb.png"}],"result":"SUCCESS","precondition":false,"level":0},{"number":3,"description":"The first heading should be \u0027Mount Everest\u0027","duration":622,"startTime":"2023-01-22T16:13:38.049317299Z[Etc/UTC]","screenshots":[{"screenshot":"b9cf047bbb123c27c2b654e585627d8511a44eccdd9143388660055dc83782bb.png","htmlSource":"pagesource15743897780381017371.html","timeStamp":1674404018483,"screenshotName":"b9cf047bbb123c27c2b654e585627d8511a44eccdd9143388660055dc83782bb.png"}],"result":"SUCCESS","precondition":false,"level":0}],"userStory":{"id":"starter.wikipedia.WhenSearchingForTerms","storyName":"When searching for terms","displayName":"When searching for terms","storyClassName":"starter.wikipedia.WhenSearchingForTerms","path":"starter.wikipedia","type":"story"},"featureTag":{"name":"Wikipedia/When searching for terms","type":"story","displayName":"Wikipedia/When searching for terms"},"title":"Search by single keyword","tags":[{"name":"Wikipedia/When searching for terms","type":"story","displayName":"Wikipedia/When searching for terms"}],"startTime":"2023-01-22T16:13:27.809788416Z[Etc/UTC]","duration":10874,"projectKey":"","sessionId":"861294b519d1717ebe931199b3e9033e","driver":"chrome","isManualTestingUpToDate":false,"manual":false,"testSource":"JUnit5","order":0,"result":"SUCCESS"}